doc/source/conf.py
doc/source/_themes/alabaster/__init__.py
doc/source/_themes/alabaster/_version.py
doc/source/_themes/alabaster/support.py
neomodantic/__init__.py
neomodantic/_version.py
neomodantic/config.py
neomodantic/exceptions.py
neomodantic/hooks.py
neomodantic/match_q.py
neomodantic/properties.py
neomodantic/util.py
neomodantic/_async_compat/util.py
neomodantic/async_/__init__.py
neomodantic/async_/cardinality.py
neomodantic/async_/core.py
neomodantic/async_/match.py
neomodantic/async_/path.py
neomodantic/async_/property_manager.py
neomodantic/async_/relationship.py
neomodantic/async_/relationship_manager.py
neomodantic/contrib/__init__.py
neomodantic/contrib/spatial_properties.py
neomodantic/contrib/async_/semi_structured.py
neomodantic/contrib/sync_/semi_structured.py
neomodantic/integration/numpy.py
neomodantic/integration/pandas.py
neomodantic/scripts/__init__.py
neomodantic/scripts/neomodel_generate_diagram.py
neomodantic/scripts/neomodel_inspect_database.py
neomodantic/scripts/neomodel_install_labels.py
neomodantic/scripts/neomodel_remove_labels.py
neomodantic/scripts/utils.py
neomodantic/sync_/__init__.py
neomodantic/sync_/cardinality.py
neomodantic/sync_/core.py
neomodantic/sync_/match.py
neomodantic/sync_/path.py
neomodantic/sync_/property_manager.py
neomodantic/sync_/relationship.py
neomodantic/sync_/relationship_manager.py
test/__init__.py
test/conftest.py
test/diagram_classes.py
test/test_scripts.py
test/_async_compat/__init__.py
test/_async_compat/mark_decorator.py
test/async_/__init__.py
test/async_/conftest.py
test/async_/test_alias.py
test/async_/test_batch.py
test/async_/test_cardinality.py
test/async_/test_connection.py
test/async_/test_cypher.py
test/async_/test_database_management.py
test/async_/test_dbms_awareness.py
test/async_/test_driver_options.py
test/async_/test_exceptions.py
test/async_/test_hooks.py
test/async_/test_indexing.py
test/async_/test_issue112.py
test/async_/test_issue283.py
test/async_/test_issue600.py
neomodantic-0.0.533a0.dist-info/AUTHORS.txt
neomodantic-0.0.533a0.dist-info/LICENSE
neomodantic-0.0.533a0.dist-info/METADATA
neomodantic-0.0.533a0.dist-info/WHEEL
neomodantic-0.0.533a0.dist-info/top_level.txt
neomodantic-0.0.533a0.dist-info/RECORD
